bitmex_websocket/__init__.py
bitmex_websocket/_bitmex_websocket.py
bitmex_websocket/_instrument.py
bitmex_websocket/_settings_base.py
bitmex_websocket/constants.py
bitmex_websocket/settings.py
bitmex_websocket/auth/__init__.py
bitmex_websocket/auth/api_key_auth.py
bitmex_websocket-0.3.5.dist-info/LICENSE
bitmex_websocket-0.3.5.dist-info/METADATA
bitmex_websocket-0.3.5.dist-info/WHEEL
bitmex_websocket-0.3.5.dist-info/top_level.txt
bitmex_websocket-0.3.5.dist-info/zip-safe
bitmex_websocket-0.3.5.dist-info/RECORD
