Metadata-Version: 2.1
Name: bitmex-websocket
Version: 0.3.5
Summary: Bitmex websocket API
Home-page: https://github.com/joliveros/bitmex-websocket
Author: José Oliveros
Author-email: Jose Oliveros <jose.oliveros.1983@gmail.com>
License: The MIT License (MIT)
Project-URL: Homepage, https://github.com/joliveros/bitmex-websocket
Project-URL: Bug Tracker, https://github.com/joliveros/bitmex-websocket/issues
Keywords: bitmex,websocket,bot,cryptocurrency
Classifier: Programming Language :: Python :: 3
Classifier: License :: OSI Approved :: MIT License
Classifier: Operating System :: OS Independent
Requires-Python: >=3.7
License-File: LICENSE
Requires-Dist: alog (==1.2.0)
Requires-Dist: bleach (==6.0.0)
Requires-Dist: build (==0.10.0)
Requires-Dist: certifi (==2022.12.7)
Requires-Dist: cffi (==1.15.1)
Requires-Dist: charset-normalizer (==3.1.0)
Requires-Dist: click (==8.1.3)
Requires-Dist: cryptography (==40.0.2)
Requires-Dist: docutils (==0.19)
Requires-Dist: idna (==3.4)
Requires-Dist: importlib-metadata (==6.6.0)
Requires-Dist: jaraco.classes (==3.2.3)
Requires-Dist: jeepney (==0.8.0)
Requires-Dist: keyring (==23.13.1)
Requires-Dist: markdown-it-py (==2.2.0)
Requires-Dist: mdurl (==0.1.2)
Requires-Dist: more-itertools (==9.1.0)
Requires-Dist: packaging (==23.1)
Requires-Dist: pipfreeze (==2.0.3)
Requires-Dist: pkginfo (==1.9.6)
Requires-Dist: pycparser (==2.21)
Requires-Dist: pyee (==9.0.4)
Requires-Dist: Pygments (==2.15.1)
Requires-Dist: pyproject-hooks (==1.0.0)
Requires-Dist: readme-renderer (==37.3)
Requires-Dist: requests (==2.28.2)
Requires-Dist: requests-toolbelt (==0.10.1)
Requires-Dist: rfc3986 (==2.0.0)
Requires-Dist: rich (==13.3.4)
Requires-Dist: SecretStorage (==3.3.3)
Requires-Dist: semver (==3.0.0)
Requires-Dist: setuptools (==65.5.1)
Requires-Dist: six (==1.16.0)
Requires-Dist: twine (==4.0.2)
Requires-Dist: typing-extensions (==4.5.0)
Requires-Dist: urllib3 (==1.26.15)
Requires-Dist: webencodings (==0.5.1)
Requires-Dist: websocket-client (==1.5.1)
Requires-Dist: wheel (==0.40.0)
Requires-Dist: zipp (==3.15.0)
